magicli.py
magicli-1.1.1.dist-info/WHEEL
magicli-1.1.1.dist-info/METADATA
magicli-1.1.1.dist-info/RECORD
