Metadata-Version: 2.4
Name: magicli
Version: 1.1.1
Summary: Automatically generates a CLI from functions.
Author-email: Patrick Elmer <patrick@elmer.ws>
Requires-Dist: pytest ; extra == "dev"
Project-URL: Home, https://github.com/PatrickElmer/magicli
Provides-Extra: dev
